Metadata-Version: 2.1
Name: network-serializer
Version: 1.0.2
Summary: A Python module to help encode and decode network packets.
Home-page: https://github.com/bubblemans/network-serializer
Author: Alvin Lin
Author-email: hungyeh.alvin.lin@gmail.com
License: MIT
Download-URL: https://github.com/bubblemans/network-serializer/archive/v1.0.1.tar.gz
Keywords: network,serilize,serializer,encode,decode,packet
Platform: UNKNOWN
Classifier: Development Status :: 3 - Alpha
Classifier: Intended Audience :: Developers
Classifier: Topic :: Software Development :: Build Tools
Classifier: License :: OSI Approved :: MIT License
Classifier: Programming Language :: Python :: 3
Classifier: Programming Language :: Python :: 3.4
Classifier: Programming Language :: Python :: 3.5
Classifier: Programming Language :: Python :: 3.6
Classifier: Programming Language :: Python :: 3.7
